odoo/addons/mrp_order_report_lot/README.rst
odoo/addons/mrp_order_report_lot/__init__.py
odoo/addons/mrp_order_report_lot/__manifest__.py
odoo/addons/mrp_order_report_lot/i18n/it.po
odoo/addons/mrp_order_report_lot/i18n/mrp_order_report_lot.pot
odoo/addons/mrp_order_report_lot/models/__init__.py
odoo/addons/mrp_order_report_lot/models/stock_move.py
odoo/addons/mrp_order_report_lot/readme/CONTRIBUTORS.rst
odoo/addons/mrp_order_report_lot/readme/DESCRIPTION.rst
odoo/addons/mrp_order_report_lot/reports/mrp_order_report.xml
odoo/addons/mrp_order_report_lot/static/description/icon.png
odoo/addons/mrp_order_report_lot/static/description/index.html
odoo_addon_mrp_order_report_lot-16.0.1.0.0.4.dist-info/METADATA
odoo_addon_mrp_order_report_lot-16.0.1.0.0.4.dist-info/WHEEL
odoo_addon_mrp_order_report_lot-16.0.1.0.0.4.dist-info/top_level.txt
odoo_addon_mrp_order_report_lot-16.0.1.0.0.4.dist-info/RECORD
